pidi_display_st7789/__init__.py
pidi_display_st7789-0.1.2.dist-info/METADATA
pidi_display_st7789-0.1.2.dist-info/WHEEL
pidi_display_st7789-0.1.2.dist-info/entry_points.txt
pidi_display_st7789-0.1.2.dist-info/top_level.txt
pidi_display_st7789-0.1.2.dist-info/RECORD
