Metadata-Version: 2.1
Name: pidi-display-st7789
Version: 0.1.2
Summary: pidi plugin for display output using an ST7789 1.3" 240x240 SPI LCD.
Home-page: https://github.com/pimoroni/pidi-plugins
Author: Philip Howard
Author-email: phil@pimoroni.com
License: MIT
Platform: UNKNOWN
Classifier: Environment :: X11 Applications
Classifier: License :: OSI Approved :: MIT License
Classifier: Operating System :: POSIX :: Linux
Classifier: Programming Language :: Python :: 3.6
Requires-Python: >=2.7
Requires-Dist: Pillow
Requires-Dist: pidi-display-pil (>=0.1.0)
Requires-Dist: st7789
